webutil/__init__.py
webutil/webdriver.py
webutil-0.0.1.dist-info/LICENSE
webutil-0.0.1.dist-info/METADATA
webutil-0.0.1.dist-info/WHEEL
webutil-0.0.1.dist-info/top_level.txt
webutil-0.0.1.dist-info/RECORD
